frost_rs-1.0.0.dist-info/METADATA
frost_rs-1.0.0.dist-info/WHEEL
frost_rs/__init__.py
frost_rs/frost_rs.cp311-win_amd64.pyd
frost_rs-1.0.0.dist-info/RECORD
